memcache_lameh/__init__.py
memcache_lameh/emcache_client.py
memcache_lameh/interfaces/__init__.py
memcache_lameh/interfaces/emcache_client_interface.py
memcache_lameh/interfaces.py
memcache_lameh/utils/__init__.py
memcache_lameh/utils/lib.py
memcache_lameh/utils/logger.py
memcache_lameh-0.1.0.dist-info/METADATA
memcache_lameh-0.1.0.dist-info/WHEEL
memcache_lameh-0.1.0.dist-info/RECORD
