Metadata-Version: 2.3
Name: memcache-lameh
Version: 0.1.0
Summary: 
Author: zouno23
Author-email: medazizbenhmidene@gmail.com
Requires-Python: >=3.11
Classifier: Programming Language :: Python :: 3
Classifier: Programming Language :: Python :: 3.11
Classifier: Programming Language :: Python :: 3.12
Classifier: Programming Language :: Python :: 3.13
Requires-Dist: emcache (>=1.3.1)
